setup.cfg
setup.py
smite/__init__.py
smite/cli.py
smite/client.py
smite/exceptions.py
smite/proxy.py
smite/servant.py
smite/tests.py
smite/tweens.py
smite/utils.py
smite.egg-info/PKG-INFO
smite.egg-info/SOURCES.txt
smite.egg-info/dependency_links.txt
smite.egg-info/entry_points.txt
smite.egg-info/not-zip-safe
smite.egg-info/requires.txt
smite.egg-info/top_level.txt