Metadata-Version: 1.1
Name: smite
Version: 0.2a3
Summary: Simple RPC-like messaging library based on ZMQ
Home-page: https://github.com/pmdz/smite
Author: pmdez
Author-email: pawel@mewritescode.com
License: UNKNOWN
Platform: UNKNOWN
Classifier: Programming Language :: Python
Classifier: Development Status :: 3 - Alpha
